tones/__init__.py
tones/_utils.py
tones/mixer.py
tones/tone.py
tones-1.0.1.dist-info/DESCRIPTION.rst
tones-1.0.1.dist-info/METADATA
tones-1.0.1.dist-info/RECORD
tones-1.0.1.dist-info/WHEEL
tones-1.0.1.dist-info/metadata.json
tones-1.0.1.dist-info/top_level.txt
